drone_2d_custom_gym_env/Drone.py
drone_2d_custom_gym_env/__init__.py
drone_2d_custom_gym_env/drone_2d_env.py
drone_2d_custom_gym_env/event_handler.py
drone_2d_custom_gym_env/img/icon.png
drone_2d_custom_gym_env/img/shade.png
drone_2d_custom_gym_env-1.3.3.dist-info/METADATA
drone_2d_custom_gym_env-1.3.3.dist-info/WHEEL
drone_2d_custom_gym_env-1.3.3.dist-info/top_level.txt
drone_2d_custom_gym_env-1.3.3.dist-info/RECORD
