Metadata-Version: 2.1
Name: drone-2d-custom-gym-env
Version: 1.3.3
Summary: OpenAI Gym environment designed for training RL agents to control the flight of a two-dimensional drone.
Home-page: https://github.com/marek-robak/Drone-2d-custom-gym-env-for-reinforcement-learning.git
Download-URL: https://pypi.org/project/drone-2d-custom-gym-env/
Author: Marek Robak
Author-email: maro.robak@gmail.com
License: UNKNOWN
Keywords: reinforcement learning,gym environment,StableBaselines3,OpenAI Gym
Platform: UNKNOWN
Requires-Dist: gym
Requires-Dist: pygame
Requires-Dist: pymunk
Requires-Dist: numpy
Requires-Dist: stable-baselines3[extra]
